{
  "name": "search_commits",
  "description": "Search for commits across GitHub repositories using GitHub's commit search syntax. Useful for finding specific changes, authors, or messages across one or many repositories. Searches the default branch only.",
  "inputSchema": {
    "type": "object",
    "properties": {
      "order": {
        "type": "string",
        "description": "Sort order",
        "enum": [
          "asc",
          "desc"
        ]
      },
      "page": {
        "type": "number",
        "description": "Page number for pagination (min 1)",
        "minimum": 1
      },
      "perPage": {
        "type": "number",
        "description": "Results per page for pagination (min 1, max 100)",
        "minimum": 1,
        "maximum": 100
      },
      "query": {
        "type": "string",
        "description": "Commit search query (GitHub commit search REST). Searches commit messages on the default branch only. Scope the search with `repo:owner/repo`, `org:`, or `user:` (queries without a scope qualifier match across all of GitHub and are usually not what you want). Other qualifiers: `author:`, `committer:`, `author-name:`, `committer-name:`, `author-email:`, `committer-email:`, `author-date:`, `committer-date:` (supports `>`, `<`, `>=`, `<=`, and `YYYY-MM-DD..YYYY-MM-DD` ranges), `merge:true|false`, `hash:`, `tree:`, `parent:`, `is:public`. Examples: `repo:owner/repo fix panic`; `org:github author:defunkt committer-date:>=2024-01-01`; `\"refactor cache\" repo:o/r`; `hash:abc1234 repo:o/r`."
      },
      "sort": {
        "type": "string",
        "description": "Sort by author or committer date (defaults to best match)",
        "enum": [
          "author-date",
          "committer-date"
        ]
      }
    },
    "required": [
      "query"
    ]
  }
}